visitoolkit_eventsystem/__init__.py
visitoolkit_eventsystem/eventsystem.py
visitoolkit_eventsystem-0.1.5.dist-info/METADATA
visitoolkit_eventsystem-0.1.5.dist-info/RECORD
visitoolkit_eventsystem-0.1.5.dist-info/WHEEL
visitoolkit_eventsystem-0.1.5.dist-info/top_level.txt
