Metadata-Version: 2.1
Name: visitoolkit-eventsystem
Version: 0.1.5
Summary: minimalistic event system (a bag of handlers) 
Home-page: https://github.com/stefanbraun-private/visitoolkit_eventsystem
Author: Stefan Braun
Author-email: sbraun@datacomm.ch
License: GPL-3.0
Platform: UNKNOWN
